Workbook

Sheet Estimate Summary
B2: 101 Meydenbauer · Q1 2027 Budget Price
B3: Bellevue, Washington · Non-union / open shop · Project 25-048 · Building B · Units B101–B104
B5: Base bid estimate
B7: Direct construction cost | C7: =SUMIFS('Priced Takeoff'!$V$6:$V$131,'Priced Takeoff'!$C$6:$C$131,"<>Alternate*") -> 312876.07 | E7: ROM budget estimate — not a contractor bid. Planning range reflects incomplete field verification and market quotation; it is not a guaranteed accuracy interval.
B8: Estimating / field contingency | C8: =C7*Assumptions!$C$7 -> 46931.411
B9: Subtotal | C9: =C7+C8 -> 359807.48
B10: General contractor overhead | C10: =C9*Assumptions!$C$8 -> 28784.599
B11: Contractor profit | C11: =(C9+C10)*Assumptions!$C$9 -> 19429.604 | E11: Q1 2027 pricing: 1.25% escalation from Q4 2026 inputs. Base bid includes all contract allowances and provisional field-verification scopes listed in the Priced Takeoff. Alternates are excluded.
B12: Performance / payment bond | C12: =(C9+C10+C11)*Assumptions!$C$10 -> 4080.2169
B13: Pre-tax contract budget | C13: =SUM(C9:C12) -> 412101.9
B14: Bellevue retail sales tax | C14: =C13*Assumptions!$C$11 -> 42034.394
B15: BASE BID TOTAL — Q1 2027 | C15: =C13+C14 -> 454136.3 | E15: Tax assumption: 10.2% Bellevue retail sales tax applied to the total custom-construction contract price. Confirm Q1 2027 tax rate and contractor tax treatment before submission.
B16: Low planning range | C16: =C15*Assumptions!$C$12 -> 386015.85
B17: High planning range | C17: =C15*Assumptions!$C$13 -> 567670.37
B20: Owner alternates — standalone, excluded from base bid
B22: Alternate | C22: Direct cost | D22: Pre-tax budget | E22: Sales tax | F22: Total if accepted
B23: 1 · Floor-mounted toilets (8 EA) | C23: =SUMIFS('Priced Takeoff'!$V$6:$V$131,'Priced Takeoff'!$C$6:$C$131,"Alternate 1") -> 13820.094 | D23: =C23*(1+Assumptions!$C$7)*(1+Assumptions!$C$8)*(1+Assumptions!$C$9)*(1+Assumptions!$C$10) -> 18203.012 | E23: =D23*Assumptions!$C$11 -> 1856.7072 | F23: =D23+E23 -> 20059.719
B24: 2 · Like-in-kind bathtubs (4 EA) | C24: =SUMIFS('Priced Takeoff'!$V$6:$V$131,'Priced Takeoff'!$C$6:$C$131,"Alternate 2") -> 8490.2321 | D24: =C24*(1+Assumptions!$C$7)*(1+Assumptions!$C$8)*(1+Assumptions!$C$9)*(1+Assumptions!$C$10) -> 11182.833 | E24: =D24*Assumptions!$C$11 -> 1140.6489 | F24: =D24+E24 -> 12323.482
B25: Base + both alternates | F25: =C15+F23+F24 -> 486519.5
B28: Direct-cost distribution
B30: Work product | C30: Direct cost | D30: Share of base direct | F30: Unit direct costs (excluding building-wide allocations)
B31: WP1 | C31: =SUMIFS('Priced Takeoff'!$V$6:$V$131,'Priced Takeoff'!$C$6:$C$131,B31) -> 160985.57 | D31: =C31/$C$7 -> 0.5145346 | F31: B101 | G31: =SUMIFS('Priced Takeoff'!$V$6:$V$131,'Priced Takeoff'!$F$6:$F$131,F31,'Priced Takeoff'!$C$6:$C$131,"<>Alternate*") -> 20490.793
B32: WP2 | C32: =SUMIFS('Priced Takeoff'!$V$6:$V$131,'Priced Takeoff'!$C$6:$C$131,B32) -> 1216.3705 | D32: =C32/$C$7 -> 0.0038877071 | F32: B102 | G32: =SUMIFS('Priced Takeoff'!$V$6:$V$131,'Priced Takeoff'!$F$6:$F$131,F32,'Priced Takeoff'!$C$6:$C$131,"<>Alternate*") -> 29661.857
B33: WP3 | C33: =SUMIFS('Priced Takeoff'!$V$6:$V$131,'Priced Takeoff'!$C$6:$C$131,B33) -> 4481.325 | D33: =C33/$C$7 -> 0.014323003 | F33: B103 | G33: =SUMIFS('Priced Takeoff'!$V$6:$V$131,'Priced Takeoff'!$F$6:$F$131,F33,'Priced Takeoff'!$C$6:$C$131,"<>Alternate*") -> 36635.978
B34: Allowance | C34: =SUMIFS('Priced Takeoff'!$V$6:$V$131,'Priced Takeoff'!$C$6:$C$131,B34) -> 146192.81 | D34: =C34/$C$7 -> 0.46725469 | F34: B104 | G34: =SUMIFS('Priced Takeoff'!$V$6:$V$131,'Priced Takeoff'!$F$6:$F$131,F34,'Priced Takeoff'!$C$6:$C$131,"<>Alternate*") -> 64700.141
B38: Before using this estimate: verify underground routes and inverts, structural demolition protocol, wall / fire assemblies, actual finish boundaries, radiant-floor scope, fixture configurations, final EHF-2 selection, supplier quotes, subcontractor coverage, permit fees, schedule, tax and bond. No price is included for Buildings A or C, upper-floor finish work, replacement of the 8-inch side sewer, or unforeseeable utility / structural repairs.

Sheet Assumptions
B2: Pricing assumptions · Bellevue · Q1 2027
B3: Open-shop / non-union budget estimate in first-quarter 2027 dollars. Blue cells are editable commercial and estimating inputs.
B5: Input | C5: Value | D5: Unit | E5: Application / source
B6: Q1 2027 escalation from Q4 2026 | C6: 0.0125 | D6: % | E6: Estimator assumption informed by Seattle cost-index trends; applied to material, equipment, other direct costs and crew rates.
B7: Estimating / field contingency | C7: 0.15 | D7: % | E7: Coordinating-model and occupied-renovation uncertainty; not a contractor-quote allowance.
B8: General contractor overhead | C8: 0.08 | D8: % | E8: Corporate overhead, insurance and administration; direct project supervision remains in the takeoff.
B9: Contractor profit | C9: 0.05 | D9: % | E9: Applied after direct cost, contingency and overhead.
B10: Performance / payment bond | C10: 0.01 | D10: % | E10: Budget rate; confirm surety and contract requirement.
B11: Bellevue retail sales tax | C11: 0.102 | D11: % | E11: Applied to total custom-construction contract price per Washington DOR guidance; verify Q1 2027 rate before contract.
B12: Low planning factor | C12: 0.85 | D12: x | E12: Planning range only; not statistical confidence.
B13: High planning factor | C13: 1.25 | D13: x | E13: Planning range only; excludes major unforeseen structural / utility conditions.
B14: Base price period | C14: Q4 2026 | D14: date | E14: Market benchmarks and estimator unit-rate inputs.
B15: Estimate price period | C15: Q1 2027 | D15: date | E15: Requested pricing quarter.
B16: Labor basis | C16: Non-union / open shop | D16: text | E16: No prevailing-wage or union agreement rates used.
B17: Work schedule | C17: Normal weekday hours | D17: text | E17: Occupied, phased access and daily restoration productivity included; no overtime premium.
B18: Estimate status | C18: ROM budget — not a bid | D18: text | E18: Requires subcontractor / supplier quotes and field verification before commitment.
B22: Commercial interpretation
B24: • Addendum #1 bid-form unit prices and dollar allowances were blank; this workbook supplies independent budget prices, not awarded contract rates.
B25: • Contract allowances are priced as complete scope lines where the bid form / schedule expressly includes installation, overhead, profit, taxes and bond. For estimate transparency, those components are calculated in the Summary rather than hidden in each unit rate.
B26: • Allowance quantity adjustments must follow final accepted in-place measurement and Addendum #1 §§01 21 00 / 01 22 00. Supplier and subcontractor quotes are required before converting this budget into a bid.
B27: • Base bid excludes Alternate 1 and Alternate 2. Each alternate is priced independently in the Summary and is not included in the base total.
B28: • No additional cost is assigned to the informational concrete-volume line because the same physical work is already priced in the 700 SF concrete allowance.
B29: • Washington tax treatment is a budget assumption for a prime / general custom-construction contractor. Confirm entity role, reseller permits, jurisdiction and Q1 2027 tax rate with a tax professional.

Sheet Rate Buildups
B2: Open-shop crew rate buildups
B3: Base wages are editable Q4 2026 inputs. Burden covers payroll taxes, workers’ compensation, benefits and paid nonproductive time. Q1 2027 crew rates are formula-driven.
B5: Crew code | C5: Crew / composition | D5: Base wage ($/hr) | E5: Labor burden | F5: Burdened Q4 rate ($/hr) | G5: Q1 escalation | H5: Q1 2027 crew rate ($/hr) | I5: Basis
B6: PLUMB | C6: 1 plumber + 2 apprentices (contract 2:1 ratio) | D6: 32.67 | E6: 0.38 | F6: =D6*(1+E6) -> 45.0846 | G6: =Assumptions!$C$6 -> 0.0125 | H6: =F6*(1+G6) -> 45.648158 | I6: Local BLS plumber benchmark; open-shop blended crew input
B7: CARP | C7: Finish carpenter / cabinet restoration | D7: 38 | E7: 0.35 | F7: =D7*(1+E7) -> 51.3 | G7: =Assumptions!$C$6 -> 0.0125 | H7: =F7*(1+G7) -> 51.94125 | I7: Local BLS carpenter benchmark; open-shop input
B8: LABOR | C8: General construction labor / protection | D8: 29 | E8: 0.35 | F8: =D8*(1+E8) -> 39.15 | G8: =Assumptions!$C$6 -> 0.0125 | H8: =F8*(1+G8) -> 39.639375 | I8: Local BLS laborer benchmark; open-shop input
B9: TILE | C9: Tile setter + helper blended crew | D9: 30.5 | E9: 0.35 | F9: =D9*(1+E9) -> 41.175 | G9: =Assumptions!$C$6 -> 0.0125 | H9: =F9*(1+G9) -> 41.689687 | I9: Estimator blended open-shop crew
B10: FLOOR | C10: Wood / resilient flooring installer | D10: 36 | E10: 0.35 | F10: =D10*(1+E10) -> 48.6 | G10: =Assumptions!$C$6 -> 0.0125 | H10: =F10*(1+G10) -> 49.2075 | I10: Estimator open-shop crew
B11: CARPET | C11: Carpet installer | D11: 32 | E11: 0.35 | F11: =D11*(1+E11) -> 43.2 | G11: =Assumptions!$C$6 -> 0.0125 | H11: =F11*(1+G11) -> 43.74 | I11: Estimator open-shop crew
B12: PAINT | C12: Painter / wall-finishing crew | D12: 32 | E12: 0.35 | F12: =D12*(1+E12) -> 43.2 | G12: =Assumptions!$C$6 -> 0.0125 | H12: =F12*(1+G12) -> 43.74 | I12: Estimator open-shop crew
B13: ELEC | C13: Licensed electrician | D13: 46 | E13: 0.38 | F13: =D13*(1+E13) -> 63.48 | G13: =Assumptions!$C$6 -> 0.0125 | H13: =F13*(1+G13) -> 64.2735 | I13: Local BLS electrician benchmark; open-shop input
B14: CONC | C14: Concrete / excavation blended crew | D14: 31.5 | E14: 0.38 | F14: =D14*(1+E14) -> 43.47 | G14: =Assumptions!$C$6 -> 0.0125 | H14: =F14*(1+G14) -> 44.013375 | I14: Estimator concrete finisher + labor crew
B15: ADMIN | C15: Project administration / closeout | D15: 45 | E15: 0.3 | F15: =D15*(1+E15) -> 58.5 | G15: =Assumptions!$C$6 -> 0.0125 | H15: =F15*(1+G15) -> 59.23125 | I15: Estimator project administration input
B16: SUP | C16: Working superintendent / project supervision | D16: 50 | E16: 0.38 | F16: =D16*(1+E16) -> 69 | G16: =Assumptions!$C$6 -> 0.0125 | H16: =F16*(1+G16) -> 69.8625 | I16: Estimator direct project supervision input

Sheet Priced Takeoff
B2: Priced takeoff · Q1 2027
B3: Standalone budget pricing of the comprehensive takeoff. Quantities are carried from the validated takeoff; costs are formulas. Base-bid and alternate work remain separate.
B5: Item | C5: Work product | D5: Division | E5: Takeoff category | F5: Unit | G5: Scope description | H5: Quantity | I5: UoM | J5: Pricing method | K5: Base material / unit | L5: Q1 material / unit | M5: Labor hr / unit | N5: Crew | O5: Q1 crew $ / hr | P5: Base equip / unit | Q5: Base other / unit | R5: Material cost | S5: Labor cost | T5: Equipment cost | U5: Other direct cost | V5: Direct cost | W5: Direct unit cost | X5: Confidence | Y5: Pricing basis | Z5: Pricing note / assumption
B6: T-001 | C6: WP1 | D6: 22 — Plumbing | E6: DWV - New ABS | F6: B101 | G6: New Schedule 40 solid-core ABS, 2-inch nominal | H6: 15.382349 | I6: LF | J6: Model-derived unit rate | K6: 5.2 | L6: =K6*(1+Assumptions!$C$6) -> 5.265 | M6: 0.16 | N6: PLUMB | O6: =IFERROR(VLOOKUP(N6,'Rate Buildups'!$B$6:$H$16,7,FALSE()),0) -> 45.648158 | P6: 0.75 | Q6: 0.5 | R6: =H6*L6 -> 80.988067 | S6: =H6*M6*O6 -> 112.34814 | T6: =H6*P6*(1+Assumptions!$C$6) -> 11.680971 | U6: =H6*Q6*(1+Assumptions!$C$6) -> 7.7873142 | V6: =SUM(R6:U6) -> 212.8045 | W6: =IFERROR(V6/H6,0) -> 13.83433 | X6: Medium | Y6: Model-derived unit rate | Z6: Pipe + representative fittings / solvents; excavation and slab work priced separately
B7: T-002 | C7: WP1 | D7: 22 — Plumbing | E7: DWV - New ABS | F7: B101 | G7: New Schedule 40 solid-core ABS, 3-inch nominal | H7: 10.270985 | I7: LF | J7: Model-derived unit rate | K7: 7.4 | L7: =K7*(1+Assumptions!$C$6) -> 7.4925 | M7: 0.18 | N7: PLUMB | O7: =IFERROR(VLOOKUP(N7,'Rate Buildups'!$B$6:$H$16,7,FALSE()),0) -> 45.648158 | P7: 1 | Q7: 0.5 | R7: =H7*L7 -> 76.955355 | S7: =H7*M7*O7 -> 84.393277 | T7: =H7*P7*(1+Assumptions!$C$6) -> 10.399372 | U7: =H7*Q7*(1+Assumptions!$C$6) -> 5.1996862 | V7: =SUM(R7:U7) -> 176.94769 | W7: =IFERROR(V7/H7,0) -> 17.227918 | X7: Medium | Y7: Model-derived unit rate | Z7: Pipe + representative fittings / solvents; excavation and slab work priced separately
B8: T-003 | C8: WP1 | D8: 22 — Plumbing | E8: DWV - New ABS | F8: B101 | G8: New Schedule 40 solid-core ABS, 4-inch nominal | H8: 45.432263 | I8: LF | J8: Model-derived unit rate | K8: 10.25 | L8: =K8*(1+Assumptions!$C$6) -> 10.378125 | M8: 0.22 | N8: PLUMB | O8: =IFERROR(VLOOKUP(N8,'Rate Buildups'!$B$6:$H$16,7,FALSE()),0) -> 45.648158 | P8: 1.25 | Q8: 0.75 | R8: =H8*L8 -> 471.5017 | S8: =H8*M8*O8 -> 456.2578 | T8: =H8*P8*(1+Assumptions!$C$6) -> 57.500208 | U8: =H8*Q8*(1+Assumptions!$C$6) -> 34.500125 | V8: =SUM(R8:U8) -> 1019.7598 | W8: =IFERROR(V8/H8,0) -> 22.44572 | X8: Medium | Y8: Model-derived unit rate | Z8: Pipe + representative fittings / solvents; excavation and slab work priced separately
B9: T-004 | C9: WP1 | D9: 22 — Plumbing | E9: DWV - New ABS | F9: B101 | G9: New Schedule 40 solid-core ABS, 6-inch nominal | H9: 1.500325 | I9: LF | J9: Model-derived unit rate | K9: 18.5 | L9: =K9*(1+Assumptions!$C$6) -> 18.73125 | M9: 0.32 | N9: PLUMB | O9: =IFERROR(VLOOKUP(N9,'Rate Buildups'!$B$6:$H$16,7,FALSE()),0) -> 45.648158 | P9: 2 | Q9: 1 | R9: =H9*L9 -> 28.102963 | S9: =H9*M9*O9 -> 21.915863 | T9: =H9*P9*(1+Assumptions!$C$6) -> 3.0381581 | U9: =H9*Q9*(1+Assumptions!$C$6) -> 1.5190791 | V9: =SUM(R9:U9) -> 54.576063 | W9: =IFERROR(V9/H9,0) -> 36.37616 | X9: Medium | Y9: Model-derived unit rate | Z9: Pipe + representative fittings / solvents; excavation and slab work priced separately
B10: T-005 | C10: WP1 | D10: 22 / 09 / 26 | E10: Fixtures - Base R&R | F10: B101 | G10: Kitchen sink / cabinet | H10: 1 | I10: EA | J10: Fixture R&R unit rate | K10: 250 | L10: =K10*(1+Assumptions!$C$6) -> 253.125 | M10: 10 | N10: PLUMB | O10: =IFERROR(VLOOKUP(N10,'Rate Buildups'!$B$6:$H$16,7,FALSE()),0) -> 45.648158 | P10: 25 | Q10: 50 | R10: =H10*L10 -> 253.125 | S10: =H10*M10*O10 -> 456.48158 | T10: =H10*P10*(1+Assumptions!$C$6) -> 25.3125 | U10: =H10*Q10*(1+Assumptions!$C$6) -> 50.625 | V10: =SUM(R10:U10) -> 785.54408 | W10: =IFERROR(V10/H10,0) -> 785.54408 | X10: Medium | Y10: Fixture R&R unit rate | Z10: Existing fixture reuse unless alternate accepted
B11: T-006 | C11: WP1 | D11: 22 / 09 / 26 | E11: Fixtures - Base R&R | F11: B101 | G11: Water closets | H11: 2 | I11: EA | J11: Fixture R&R unit rate | K11: 180 | L11: =K11*(1+Assumptions!$C$6) -> 182.25 | M11: 8 | N11: PLUMB | O11: =IFERROR(VLOOKUP(N11,'Rate Buildups'!$B$6:$H$16,7,FALSE()),0) -> 45.648158 | P11: 10 | Q11: 25 | R11: =H11*L11 -> 364.5 | S11: =H11*M11*O11 -> 730.37052 | T11: =H11*P11*(1+Assumptions!$C$6) -> 20.25 | U11: =H11*Q11*(1+Assumptions!$C$6) -> 50.625 | V11: =SUM(R11:U11) -> 1165.7455 | W11: =IFERROR(V11/H11,0) -> 582.87276 | X11: Medium | Y11: Fixture R&R unit rate | Z11: Existing fixture reuse unless alternate accepted
B12: T-007 | C12: WP1 | D12: 22 / 09 / 26 | E12: Fixtures - Base R&R | F12: B101 | G12: Bathtubs | H12: 1 | I12: EA | J12: Fixture R&R unit rate | K12: 120 | L12: =K12*(1+Assumptions!$C$6) -> 121.5 | M12: 14 | N12: PLUMB | O12: =IFERROR(VLOOKUP(N12,'Rate Buildups'!$B$6:$H$16,7,FALSE()),0) -> 45.648158 | P12: 15 | Q12: 40 | R12: =H12*L12 -> 121.5 | S12: =H12*M12*O12 -> 639.07421 | T12: =H12*P12*(1+Assumptions!$C$6) -> 15.1875 | U12: =H12*Q12*(1+Assumptions!$C$6) -> 40.5 | V12: =SUM(R12:U12) -> 816.26171 | W12: =IFERROR(V12/H12,0) -> 816.26171 | X12: Medium | Y12: Fixture R&R unit rate | Z12: Existing fixture reuse unless alternate accepted
B13: T-008 | C13: WP1 | D13: 22 / 09 / 26 | E13: Fixtures - Base R&R | F13: B101 | G13: Showers / enclosures | H13: 1 | I13: EA | J13: Fixture R&R unit rate | K13: 150 | L13: =K13*(1+Assumptions!$C$6) -> 151.875 | M13: 16 | N13: PLUMB | O13: =IFERROR(VLOOKUP(N13,'Rate Buildups'!$B$6:$H$16,7,FALSE()),0) -> 45.648158 | P13: 15 | Q13: 40 | R13: =H13*L13 -> 151.875 | S13: =H13*M13*O13 -> 730.37052 | T13: =H13*P13*(1+Assumptions!$C$6) -> 15.1875 | U13: =H13*Q13*(1+Assumptions!$C$6) -> 40.5 | V13: =SUM(R13:U13) -> 937.93302 | W13: =IFERROR(V13/H13,0) -> 937.93302 | X13: Medium | Y13: Fixture R&R unit rate | Z13: Existing fixture reuse unless alternate accepted
B14: T-009 | C14: WP1 | D14: 22 / 09 / 26 | E14: Fixtures - Base R&R | F14: B101 | G14: Lavatories / cabinets | H14: 2 | I14: EA | J14: Fixture R&R unit rate | K14: 90 | L14: =K14*(1+Assumptions!$C$6) -> 91.125 | M14: 5 | N14: PLUMB | O14: =IFERROR(VLOOKUP(N14,'Rate Buildups'!$B$6:$H$16,7,FALSE()),0) -> 45.648158 | P14: 5 | Q14: 20 | R14: =H14*L14 -> 182.25 | S14: =H14*M14*O14 -> 456.48158 | T14: =H14*P14*(1+Assumptions!$C$6) -> 10.125 | U14: =H14*Q14*(1+Assumptions!$C$6) -> 40.5 | V14: =SUM(R14:U14) -> 689.35658 | W14: =IFERROR(V14/H14,0) -> 344.67829 | X14: Medium | Y14: Fixture R&R unit rate | Z14: Existing fixture reuse unless alternate accepted
B15: T-010 | C15: WP1 | D15: 22 / 09 / 26 | E15: Fixtures - Base R&R | F15: B101 | G15: Washing machines | H15: 1 | I15: EA | J15: Fixture R&R unit rate | K15: 25 | L15: =K15*(1+Assumptions!$C$6) -> 25.3125 | M15: 2 | N15: LABOR | O15: =IFERROR(VLOOKUP(N15,'Rate Buildups'!$B$6:$H$16,7,FALSE()),0) -> 39.639375 | P15: 5 | Q15: 10 | R15: =H15*L15 -> 25.3125 | S15: =H15*M15*O15 -> 79.27875 | T15: =H15*P15*(1+Assumptions!$C$6) -> 5.0625 | U15: =H15*Q15*(1+Assumptions!$C$6) -> 10.125 | V15: =SUM(R15:U15) -> 119.77875 | W15: =IFERROR(V15/H15,0) -> 119.77875 | X15: Medium | Y15: Fixture R&R unit rate | Z15: Existing fixture reuse unless alternate accepted
B16: T-011 | C16: WP1 | D16: 22 / 09 / 26 | E16: Fixtures - Base R&R | F16: B101 | G16: Dryers | H16: 1 | I16: EA | J16: Fixture R&R unit rate | K16: 15 | L16: =K16*(1+Assumptions!$C$6) -> 15.1875 | M16: 2 | N16: LABOR | O16: =IFERROR(VLOOKUP(N16,'Rate Buildups'!$B$6:$H$16,7,FALSE()),0) -> 39.639375 | P16: 5 | Q16: 10 | R16: =H16*L16 -> 15.1875 | S16: =H16*M16*O16 -> 79.27875 | T16: =H16*P16*(1+Assumptions!$C$6) -> 5.0625 | U16: =H16*Q16*(1+Assumptions!$C$6) -> 10.125 | V16: =SUM(R16:U16) -> 109.65375 | W16: =IFERROR(V16/H16,0) -> 109.65375 | X16: Medium | Y16: Fixture R&R unit rate | Z16: Existing fixture reuse unless alternate accepted
B17: T-012 | C17: WP1 | D17: 22 — Plumbing | E17: DWV - Accessories | F17: B101 | G17: Base-of-stack cleanouts | H17: 3 | I17: EA | J17: Accessory unit rate | K17: 85 | L17: =K17*(1+Assumptions!$C$6) -> 86.0625 | M17: 2.5 | N17: PLUMB | O17: =IFERROR(VLOOKUP(N17,'Rate Buildups'!$B$6:$H$16,7,FALSE()),0) -> 45.648158 | P17: 5 | Q17: 10 | R17: =H17*L17 -> 258.1875 | S17: =H17*M17*O17 -> 342.36118 | T17: =H17*P17*(1+Assumptions!$C$6) -> 15.1875 | U17: =H17*Q17*(1+Assumptions!$C$6) -> 30.375 | V17: =SUM(R17:U17) -> 646.11118 | W17: =IFERROR(V17/H17,0) -> 215.37039 | X17: Medium | Y17: Accessory unit rate | Z17: Final count and access field verify
... B131: T-126 | C131: Alternate 2 | D131: 22 / 09 | E131: Alternate - Fixtures | F131: B104 | G131: Replace existing bathtub with new like-in-kind bathtub | H131: 1 | I131: EA | J131: Owner alternate | K131: 1100 | L131: =K131*(1+Assumptions!$C$6) -> 1113.75 | M131: 16 | N131: PLUMB | O131: =IFERROR(VLOOKUP(N131,'Rate Buildups'!$B$6:$H$16,7,FALSE()),0) -> 45.648158 | P131: 25 | Q131: 250 | R131: =H131*L131 -> 1113.75 | S131: =H131*M131*O131 -> 730.37052 | T131: =H131*P131*(1+Assumptions!$C$6) -> 25.3125 | U131: =H131*Q131*(1+Assumptions!$C$6) -> 253.125 | V131: =SUM(R131:U131) -> 2122.558 | W131: =IFERROR(V131/H131,0) -> 2122.558 | X131: Low | Y131: Owner alternate | Z131: Like-in-kind tub and adjacent work; excluded from base

Sheet Pricing Sources
B2: Pricing sources & estimating basis
B3: Web benchmarks support selected inputs; they are not subcontractor or supplier quotes. All remaining unit rates, production factors and markups are explicitly identified as estimator assumptions.
B5: Source Name | C5: Source URL | D5: Used for | E5: Date / period | F5: Application and limitation
B6: U.S. Bureau of Labor Statistics — Seattle-Tacoma-Bellevue OEWS | C6: https://www.bls.gov/regions/west/news-release/occupationalemploymentandwages_seattle.htm | D6: Local construction wage benchmarks | E6: May 2025 / released 2026 | F6: Local occupational wage context; crew wages remain open-shop estimator inputs, not quoted payroll rates.
B7: Mortenson — Seattle Construction Cost Index | C7: https://www.mortenson.com/cost-index/seattle | D7: Escalation context | E7: Q2 2026 | F7: Seattle nonresidential index reported +1.71% quarterly and +3.48% year over year; workbook uses a separate 1.25% Q4-to-Q1 estimator assumption.
B8: Washington Department of Revenue — Construction tax matrix | C8: https://dor.wa.gov/education/industry-guides/construction/construction-tax-matrix | D8: Sales-tax treatment | E8: Current guidance accessed 2026 | F8: Prime / general custom construction: retail sales tax is collected on the total contract price. Confirm project-specific tax treatment.
B9: City of Bellevue 2025–2026 Adopted Budget | C9: https://bellevuewa.gov/sites/default/files/media/file/2025/2025-2026-adopted-budget.pdf | D9: Bellevue sales-tax rate | E9: 2025–2026 budget | F9: States a 10.2% total sales-tax rate; verify the effective Q1 2027 rate before contract.
B10: Home Depot — 4-inch ABS DWV pipe | C10: https://www.homedepot.com/p/Plastic-Services-4-in-x-10-ft-ABS-DWV-Pipe-ABS10-4/202564275 | D10: ABS material sanity check | E10: Accessed 2026 | F10: Retail 10-foot pipe listing; workbook material rates also include representative fittings / solvents and are not supplier quotes.
B11: Stego — StegoHome 15-mil vapor barrier | C11: https://shop.stegoindustries.com/stegohome-wrap-15-mil-vapor-and-radon-barrier-12-x-50/ | D11: Vapor-barrier material sanity check | E11: Accessed 2026 | F11: Retail roll listing; project specification requires the applicable Stego Wrap Class A system and accessories.
B12: Rubi — 2026 tile installation cost guide | C12: https://www.rubi.com/us/blog/average-cost-to-install-tile-floors/ | D12: Tile material / labor range check | E12: 2026 | F12: Broad national ranges only; workbook uses finish-specific estimator inputs and local crew rates.
B13: Seattle flooring installation cost calculator | C13: https://www.kolmo.io/calculator/flooring | D13: Seattle flooring installation range check | E13: 2026 | F13: Local consumer-cost reference; not a subcontractor quote and not a substitute for the specified assemblies.
B14: Project contract documents | C14: Addendum #1; Project Manual; Exhibit A; Exhibit B | D14: Quantities and scope | E14: September–October 2026 | F14: Contract documents control scope. Bid-form prices were blank; this workbook supplies independent budget pricing.
B15: Coordination model and comprehensive takeoff | C15: Meydenbauer_Comprehensive_Project_Takeoff.xlsx | D15: Quantities and model measurement basis | E15: 25 Oct 2026 | F15: Model-derived quantities require field verification and are not fabrication quantities.
